pyscaff/__init__.py
pyscaff/main.py
pyscaff-0.1.0.dist-info/AUTHORS
pyscaff-0.1.0.dist-info/LICENSE
pyscaff-0.1.0.dist-info/METADATA
pyscaff-0.1.0.dist-info/WHEEL
pyscaff-0.1.0.dist-info/entry_points.txt
pyscaff-0.1.0.dist-info/top_level.txt
pyscaff-0.1.0.dist-info/RECORD
